pyon/__init__.py
pyon/pyon.py
pyon/tests/__init__.py
pyon/tests/test_path_parser.py
pyon/tests/tools/__init__.py
pyon/tests/tools/print_message.py
pyon/tools/__init__.py
pyon/tools/json_generator.py
pyon/tools/path_parser.py
pyon_lib-0.1.3.dist-info/LICENSE
pyon_lib-0.1.3.dist-info/METADATA
pyon_lib-0.1.3.dist-info/WHEEL
pyon_lib-0.1.3.dist-info/top_level.txt
pyon_lib-0.1.3.dist-info/RECORD
