Metadata-Version: 2.1
Name: pyon-lib
Version: 0.1.3
Summary: Pythonic Object Notation - with native objects and path support
Home-page: https://github.com/lagmoellertim/pyon
Author: Tim-Luca Lagmöller
Author-email: hello@lagmoellertim.de
License: MIT License
Platform: UNKNOWN
Classifier: Programming Language :: Python :: 3
Classifier: License :: OSI Approved :: MIT License
Classifier: Operating System :: OS Independent
Requires-Dist: pyyaml (==5.1.1)
Requires-Dist: dicttoxml (==1.7.4)
